yassin_matrix/__init__.py
yassin_matrix/core.py
yassin_matrix-0.1.1.dist-info/METADATA
yassin_matrix-0.1.1.dist-info/WHEEL
yassin_matrix-0.1.1.dist-info/top_level.txt
yassin_matrix-0.1.1.dist-info/RECORD
