Metadata-Version: 2.4
Name: yassin-matrix
Version: 0.1.1
Summary: A simple Python library for multiplying two matrices of any size
Author: Yassin Hagenimna
Author-email: hyassin509@gmail.com
Classifier: Programming Language :: Python :: 3
Classifier: License :: OSI Approved :: MIT License
Classifier: Operating System :: OS Independent
Requires-Python: >=3.6
Dynamic: author
Dynamic: author-email
Dynamic: classifier
Dynamic: description
Dynamic: description-content-type
Dynamic: requires-python
Dynamic: summary
